README.md
setup.py
dlist/__init__.py
dlist/dlist.py
dlist.egg-info/PKG-INFO
dlist.egg-info/SOURCES.txt
dlist.egg-info/dependency_links.txt
dlist.egg-info/top_level.txt