Metadata-Version: 2.1
Name: dlist
Version: 0.52
Summary: A list of dict , each dict has only one key.
Home-page: https://github.com/ihgazni2/dlist
Author: dapeli
Author-email: terryinzaghi@163.com
License: MIT
Platform: UNKNOWN
Classifier: Environment :: Console
Classifier: Environment :: Web Environment
Classifier: Intended Audience :: End Users/Desktop
Classifier: Intended Audience :: Developers
Classifier: Intended Audience :: System Administrators
Classifier: Programming Language :: Python
